{
	"code": "0",
	"msg": "成功",
	"result": [{
		"area_id": 330000,
		"attr_ids": [],
		"is_insect": 1,
		"lat": 30.418361,
		"lng": 120.134,
		"station_id": 42,
		"station_name": "新迪稼园"
	}, {
		"area_id": 330000,
		"attr_ids": [],
		"is_insect": 1,
		"lat": 39.794472,
		"lng": 116.529332,
		"station_id": 44,
		"station_name": "站点2"
	}, {
		"area_id": 330700,
		"attr_ids": [],
		"is_insect": 1,
		"lat": 0,
		"lng": 0,
		"station_id": 46,
		"station_name": "金华市土肥站"
	}, {
		"area_id": 330212,
		"attr_ids": [],
		"is_insect": 1,
		"lat": 0,
		"lng": 0,
		"station_id": 178,
		"station_name": "鄞州区农业局"
	}, {
		"area_id": 330000,
		"attr_ids": [],
		"is_insect": 1,
		"lat": 28.971586,
		"lng": 120.074485,
		"station_id": 317,
		"station_name": "亲亲"
	}, {
		"area_id": 330100,
		"attr_ids": [],
		"is_insect": 1,
		"lat": 30.29403,
		"lng": 120.191589,
		"station_id": 318,
		"station_name": "托普测试"
	}, {
		"area_id": 330283,
		"attr_ids": [],
		"is_insect": 1,
		"lat": 30.103357,
		"lng": 121.142537,
		"station_id": 321,
		"station_name": "浙江余姚碳梅"
	}, {
		"area_id": 330103,
		"attr_ids": [],
		"is_insect": 1,
		"lat": 30.301333,
		"lng": 120.157881,
		"station_id": 326,
		"station_name": "墒情测试"
	}, {
		"area_id": 330000,
		"attr_ids": [],
		"is_insect": 1,
		"lat": 29.118608,
		"lng": 120.272256,
		"station_id": 328,
		"station_name": "bbc1"
	}, {
		"area_id": 330400,
		"attr_ids": [],
		"is_insect": 1,
		"lat": 30.653535,
		"lng": 120.816087,
		"station_id": 334,
		"station_name": "A杭州"
	}, {
		"area_id": 330103,
		"attr_ids": [],
		"is_insect": 1,
		"lat": 30.295346,
		"lng": 120.184327,
		"station_id": 342,
		"station_name": "h123站点"
	}, {
		"area_id": 330000,
		"attr_ids": [],
		"is_insect": 1,
		"lat": 29.812284,
		"lng": 120.193482,
		"station_id": 343,
		"station_name": "视频测试"
	}, {
		"area_id": 330000,
		"attr_ids": [],
		"is_insect": 1,
		"lat": 30.150142,
		"lng": 120.295816,
		"station_id": 344,
		"station_name": "139"
	}, {
		"area_id": 330103,
		"attr_ids": [1],
		"is_insect": 1,
		"lat": 30.296843,
		"lng": 120.182028,
		"station_id": 345,
		"station_name": "h123站点"
	}, {
		"area_id": 330103,
		"attr_ids": [],
		"is_insect": 1,
		"lat": 30.295346,
		"lng": 120.173979,
		"station_id": 346,
		"station_name": "h123站点"
	}, {
		"area_id": 330103,
		"attr_ids": [2],
		"is_insect": 1,
		"lat": 30.299337,
		"lng": 120.176279,
		"station_id": 347,
		"station_name": "h123站点1"
	}, {
		"area_id": 330103,
		"attr_ids": [],
		"is_insect": 1,
		"lat": 30.30283,
		"lng": 120.156732,
		"station_id": 348,
		"station_name": "h111站点"
	}, {
		"area_id": 330000,
		"attr_ids": [],
		"is_insect": 1,
		"lat": 30.325868,
		"lng": 120.155537,
		"station_id": 349,
		"station_name": "苗情摄像机站"
	}, {
		"area_id": 330105,
		"attr_ids": [],
		"is_insect": 1,
		"lat": 30.314658,
		"lng": 120.154871,
		"station_id": 350,
		"station_name": "h222站点"
	}, {
		"area_id": 330103,
		"attr_ids": [],
		"is_insect": 1,
		"lat": 30.287114,
		"lng": 120.192089,
		"station_id": 351,
		"station_name": "h555站点"
	}, {
		"area_id": 330103,
		"attr_ids": [],
		"is_insect": 1,
		"lat": 30.29834,
		"lng": 120.16823,
		"station_id": 353,
		"station_name": "墒情测试"
	}, {
		"area_id": 330000,
		"attr_ids": [],
		"is_insect": 1,
		"lat": 29.092352,
		"lng": 120.136576,
		"station_id": 357,
		"station_name": "ww"
	}, {
		"area_id": 330303,
		"attr_ids": [],
		"is_insect": 1,
		"lat": 27.676821,
		"lng": 120.948278,
		"station_id": 384,
		"station_name": "dsdas@.cc"
	}, {
		"area_id": 330185,
		"attr_ids": [],
		"is_insect": 1,
		"lat": 30.233741,
		"lng": 119.737067,
		"station_id": 390,
		"station_name": "农林"
	}, {
		"area_id": 330185,
		"attr_ids": [],
		"is_insect": 1,
		"lat": 30.230746,
		"lng": 119.729018,
		"station_id": 391,
		"station_name": "临安农林"
	}, {
		"area_id": 330106,
		"attr_ids": [1],
		"is_insect": 1,
		"lat": 30.26293,
		"lng": 120.148197,
		"station_id": 392,
		"station_name": "三墩"
	}, {
		"area_id": 330000,
		"attr_ids": [3],
		"is_insect": 1,
		"lat": 30.15464,
		"lng": 120.290067,
		"station_id": 393,
		"station_name": "wen基地"
	}, {
		"area_id": 330000,
		"attr_ids": [],
		"is_insect": 1,
		"lat": 29.170091,
		"lng": 119.958352,
		"station_id": 400,
		"station_name": "智慧"
	}, {
		"area_id": 330105,
		"attr_ids": [],
		"is_insect": 1,
		"lat": 30.327876,
		"lng": 120.169244,
		"station_id": 428,
		"station_name": "远程升级-设施农业(socket)"
	}, {
		"area_id": 330105,
		"attr_ids": [],
		"is_insect": 1,
		"lat": 30.342471,
		"lng": 120.124329,
		"station_id": 438,
		"station_name": "从vxv"
	}, {
		"area_id": 330100,
		"attr_ids": [7],
		"is_insect": 1,
		"lat": 30.28954,
		"lng": 120.136397,
		"station_id": 440,
		"station_name": "基地1"
	}, {
		"area_id": 330104,
		"attr_ids": [],
		"is_insect": 1,
		"lat": 30.298189,
		"lng": 120.203427,
		"station_id": 445,
		"station_name": "橘子基地"
	}, {
		"area_id": 330104,
		"attr_ids": [],
		"is_insect": 1,
		"lat": 30.298174,
		"lng": 120.20345,
		"station_id": 446,
		"station_name": "橘子种植"
	}, {
		"area_id": 330104,
		"attr_ids": [],
		"is_insect": 1,
		"lat": 30.304351,
		"lng": 120.196641,
		"station_id": 447,
		"station_name": "苹果基地"
	}, {
		"area_id": 330104,
		"attr_ids": [7],
		"is_insect": 1,
		"lat": 30.30061,
		"lng": 120.203719,
		"station_id": 448,
		"station_name": "蔬菜大棚"
	}, {
		"area_id": 330105,
		"attr_ids": [3],
		"is_insect": 1,
		"lat": 30.362682,
		"lng": 120.227835,
		"station_id": 460,
		"station_name": "专家消息测试基地1"
	}, {
		"area_id": 330106,
		"attr_ids": [],
		"is_insect": 1,
		"lat": 30.217023,
		"lng": 120.093592,
		"station_id": 461,
		"station_name": "专家测试基地2"
	}, {
		"area_id": 330702,
		"attr_ids": [],
		"is_insect": 1,
		"lat": 29.090404,
		"lng": 119.59189,
		"station_id": 468,
		"station_name": "大棚基地"
	}, {
		"area_id": 330105,
		"attr_ids": [],
		"is_insect": 1,
		"lat": 30.321392,
		"lng": 120.160045,
		"station_id": 471,
		"station_name": "小小基地"
	}, {
		"area_id": 330104,
		"attr_ids": [7],
		"is_insect": 1,
		"lat": 30.2547,
		"lng": 120.234765,
		"station_id": 472,
		"station_name": "荷苑基地"
	}, {
		"area_id": 330109,
		"attr_ids": [],
		"is_insect": 1,
		"lat": 29.973433,
		"lng": 120.425116,
		"station_id": 480,
		"station_name": "基地@"
	}, {
		"area_id": 330110,
		"attr_ids": [],
		"is_insect": 1,
		"lat": 30.395487,
		"lng": 120.238977,
		"station_id": 492,
		"station_name": "我的农业环境测试"
	}, {
		"area_id": 330105,
		"attr_ids": [4],
		"is_insect": 1,
		"lat": 30.39399,
		"lng": 120.091664,
		"station_id": 508,
		"station_name": "农事管理"
	}, {
		"area_id": 330105,
		"attr_ids": [5],
		"is_insect": 1,
		"lat": 30.33849,
		"lng": 120.11307,
		"station_id": 509,
		"station_name": "测试基地0921"
	}, {
		"area_id": 330105,
		"attr_ids": [1],
		"is_insect": 1,
		"lat": 30.32034,
		"lng": 120.12859,
		"station_id": 510,
		"station_name": "测试基地-09211559"
	}, {
		"area_id": 330108,
		"attr_ids": [],
		"is_insect": 1,
		"lat": 30.181095,
		"lng": 120.177422,
		"station_id": 932,
		"station_name": "杭州滨江果业有限公司"
	}, {
		"area_id": 330703,
		"attr_ids": [7],
		"is_insect": 1,
		"lat": 29.16958,
		"lng": 119.77893,
		"station_id": 933,
		"station_name": "物联网新版"
	}, {
		"area_id": 330105,
		"attr_ids": [],
		"is_insect": 1,
		"lat": 30.25302,
		"lng": 120.18309,
		"station_id": 935,
		"station_name": "fbox测试基地"
	}]
}